qml_hcs-0.2.0.dist-info/licenses/LICENSE
qmlhc/__init__.py
qmlhc/backends/__init__.py
qmlhc/backends/cpp_backend.py
qmlhc/backends/pennylane_backend.py
qmlhc/backends/qiskit_backend.py
qmlhc/callbacks/__init__.py
qmlhc/callbacks/base.py
qmlhc/callbacks/depth_control.py
qmlhc/callbacks/telemetry.py
qmlhc/core/__init__.py
qmlhc/core/backend.py
qmlhc/core/model.py
qmlhc/core/registry.py
qmlhc/core/types.py
qmlhc/examples/__init__.py
qmlhc/examples/ex_minimal_core_demo.py
qmlhc/hc/__init__.py
qmlhc/hc/graph.py
qmlhc/hc/node.py
qmlhc/hc/policy.py
qmlhc/loss/__init__.py
qmlhc/loss/coherence.py
qmlhc/loss/consistency.py
qmlhc/loss/task.py
qmlhc/metrics/__init__.py
qmlhc/metrics/anomalies.py
qmlhc/metrics/control.py
qmlhc/metrics/forecasting.py
qmlhc/optim/__init__.py
qmlhc/optim/api.py
qmlhc/optim/registry_numpy.py
qmlhc/optim/numpy_optim/__init__.py
qmlhc/optim/numpy_optim/adam.py
qmlhc/optim/numpy_optim/dual_ascent.py
qmlhc/optim/numpy_optim/finite_diff.py
qmlhc/optim/numpy_optim/init.py
qmlhc/optim/numpy_optim/kfac.py
qmlhc/optim/numpy_optim/mpc.py
qmlhc/optim/numpy_optim/natural_grad.py
qmlhc/optim/numpy_optim/spsa.py
qmlhc/optim/numpy_optim/trust_region.py
qmlhc/optim/numpy_optim/utils.py
qmlhc/predictors/__init__.py
qmlhc/predictors/anticipator.py
qmlhc/predictors/projector.py
qml_hcs-0.2.0.dist-info/METADATA
qml_hcs-0.2.0.dist-info/WHEEL
qml_hcs-0.2.0.dist-info/entry_points.txt
qml_hcs-0.2.0.dist-info/top_level.txt
qml_hcs-0.2.0.dist-info/RECORD
