Metadata-Version: 2.4
Name: qml-hcs
Version: 0.2.0
Summary: Quantum Machine Learning with hypercausal feedback for non-stationary environments.
Author: Héctor Mozo
Author-email: Neureonmindflux Research Lab <contact@neureonmindfluxlab.org>
License: BSD-3-Clause
Project-URL: Homepage, https://github.com/Neureonmindflux-Research-Lab/qml-hcs
Project-URL: Issues, https://github.com/Neureonmindflux-Research-Lab/qml-hcs/issues
Project-URL: Documentation, https://qml-hcs.readthedocs.io
Keywords: quantum-machine-learning,hypercausal,non-stationary,forecasting,control,anomaly-detection,quantum computing,quantum ai,qnn,physics-informed-ai
Classifier: Development Status :: 3 - Alpha
Classifier: Intended Audience :: Science/Research
Classifier: License :: OSI Approved :: BSD License
Classifier: Operating System :: OS Independent
Classifier: Programming Language :: Python :: 3
Classifier: Programming Language :: Python :: 3 :: Only
Classifier: Programming Language :: Python :: 3.9
Classifier: Programming Language :: Python :: 3.10
Classifier: Programming Language :: Python :: 3.11
Classifier: Programming Language :: Python :: 3.12
Classifier: Topic :: Scientific/Engineering
Classifier: Topic :: Scientific/Engineering :: Artificial Intelligence
Classifier: Topic :: Scientific/Engineering :: Physics
Classifier: Topic :: Software Development :: Libraries
Classifier: Topic :: Software Development :: Libraries :: Python Modules
Requires-Python: >=3.9
License-File: LICENSE
Requires-Dist: numpy>=1.23
Requires-Dist: scipy>=1.10
Requires-Dist: typing-extensions>=4.6
Provides-Extra: qiskit
Requires-Dist: qiskit>=1.2; extra == "qiskit"
Provides-Extra: pennylane
Requires-Dist: pennylane>=0.36; extra == "pennylane"
Provides-Extra: torch
Requires-Dist: torch>=2.2; extra == "torch"
Provides-Extra: jax
Requires-Dist: jax~=0.6.0; extra == "jax"
Requires-Dist: jaxlib~=0.6.0; extra == "jax"
Provides-Extra: viz
Requires-Dist: matplotlib>=3.8; extra == "viz"
Requires-Dist: pandas>=2.1; extra == "viz"
Provides-Extra: dev
Requires-Dist: numpy>=1.26; extra == "dev"
Requires-Dist: matplotlib>=3.8; extra == "dev"
Requires-Dist: ruff>=0.6.0; extra == "dev"
Requires-Dist: mypy>=1.7.0; extra == "dev"
Requires-Dist: build>=1.2.1; extra == "dev"
Requires-Dist: twine>=5.0.0; extra == "dev"
Provides-Extra: docs
Requires-Dist: numpy>=1.26; extra == "docs"
Requires-Dist: matplotlib>=3.8; extra == "docs"
Requires-Dist: pandas>=2.1; extra == "docs"
Requires-Dist: sphinx>=7.3; extra == "docs"
Requires-Dist: sphinx-book-theme; extra == "docs"
Requires-Dist: furo; extra == "docs"
Requires-Dist: myst-parser; extra == "docs"
Requires-Dist: sphinx-autodoc-typehints; extra == "docs"
Requires-Dist: sphinx-copybutton; extra == "docs"
Requires-Dist: sphinx-rtd-theme; extra == "docs"
Requires-Dist: jinja2>=3.1; extra == "docs"
Requires-Dist: docutils>=0.20; extra == "docs"
Requires-Dist: sphinxcontrib-programoutput>=0.18; extra == "docs"
Provides-Extra: test
Requires-Dist: numpy>=1.26; extra == "test"
Requires-Dist: pytest>=8.1; extra == "test"
Requires-Dist: pytest-cov>=4.1; extra == "test"
Requires-Dist: coverage>=7.4; extra == "test"
Requires-Dist: matplotlib>=3.8; extra == "test"
Requires-Dist: pandas>=2.1; extra == "test"
Provides-Extra: all
Requires-Dist: qiskit>=1.2; extra == "all"
Requires-Dist: pennylane>=0.36; extra == "all"
Requires-Dist: torch>=2.2; extra == "all"
Requires-Dist: jax~=0.6.0; extra == "all"
Requires-Dist: jaxlib~=0.6.0; extra == "all"
Requires-Dist: matplotlib>=3.8; extra == "all"
Requires-Dist: pandas>=2.1; extra == "all"
Requires-Dist: ruff>=0.6.0; extra == "all"
Requires-Dist: mypy>=1.7.0; extra == "all"
Requires-Dist: build>=1.2.1; extra == "all"
Requires-Dist: twine>=5.0.0; extra == "all"
Requires-Dist: sphinx>=7.3; extra == "all"
Requires-Dist: sphinx-book-theme; extra == "all"
Requires-Dist: furo; extra == "all"
Requires-Dist: myst-parser; extra == "all"
Requires-Dist: sphinx-autodoc-typehints; extra == "all"
Requires-Dist: sphinx-copybutton; extra == "all"
Requires-Dist: sphinx-rtd-theme; extra == "all"
Requires-Dist: jinja2>=3.1; extra == "all"
Requires-Dist: docutils>=0.20; extra == "all"
Requires-Dist: sphinxcontrib-programoutput>=0.18; extra == "all"
Requires-Dist: pytest>=8.1; extra == "all"
Requires-Dist: pytest-cov>=4.1; extra == "all"
Requires-Dist: coverage>=7.4; extra == "all"
Requires-Dist: numpy>=1.23; extra == "all"
Dynamic: license-file
